login_tests/__init__.py
login_tests/base_login_test.py
login_tests/microsoft_login_test.py
login_tests/utils/__init__.py
login_tests/utils/des_cap.py
login_tests/utils/driver_utils.py
login_tests-1.1.3.dist-info/METADATA
login_tests-1.1.3.dist-info/WHEEL
login_tests-1.1.3.dist-info/entry_points.txt
login_tests-1.1.3.dist-info/top_level.txt
login_tests-1.1.3.dist-info/RECORD
