Metadata-Version: 2.1
Name: login_tests
Version: 1.1.3
Requires-Dist: Appium-Python-Client==2.0.0
Requires-Dist: selenium>=4.0.0
Requires-Dist: pytest>=6.0.0
